odoo/addons/delivery_carrier_picking_valid/README.rst
odoo/addons/delivery_carrier_picking_valid/__init__.py
odoo/addons/delivery_carrier_picking_valid/__manifest__.py
odoo/addons/delivery_carrier_picking_valid/i18n/delivery_carrier_picking_valid.pot
odoo/addons/delivery_carrier_picking_valid/i18n/it.po
odoo/addons/delivery_carrier_picking_valid/models/__init__.py
odoo/addons/delivery_carrier_picking_valid/models/delivery_carrier.py
odoo/addons/delivery_carrier_picking_valid/readme/CONTRIBUTORS.md
odoo/addons/delivery_carrier_picking_valid/readme/DESCRIPTION.md
odoo/addons/delivery_carrier_picking_valid/static/description/icon.png
odoo/addons/delivery_carrier_picking_valid/static/description/index.html
odoo/addons/delivery_carrier_picking_valid/tests/__init__.py
odoo/addons/delivery_carrier_picking_valid/tests/common.py
odoo/addons/delivery_carrier_picking_valid/tests/test_picking_valid.py
odoo_addon_delivery_carrier_picking_valid-18.0.1.0.0.5.dist-info/METADATA
odoo_addon_delivery_carrier_picking_valid-18.0.1.0.0.5.dist-info/WHEEL
odoo_addon_delivery_carrier_picking_valid-18.0.1.0.0.5.dist-info/top_level.txt
odoo_addon_delivery_carrier_picking_valid-18.0.1.0.0.5.dist-info/RECORD
