Metadata-Version: 2.1
Name: odoo-addon-delivery_carrier_picking_valid
Version: 18.0.1.0.0.5
Requires-Python: >=3.10
Requires-Dist: odoo-addon-stock_picking_volume==18.0.*
Requires-Dist: odoo==18.0.*
Summary: Checks if a transfer matches carrier requirements
Home-page: https://github.com/OCA/delivery-carrier
License: AGPL-3
Author: Camptocamp, BCIM, Odoo Community Association (OCA)
Author-email: support@odoo-community.org
Classifier: Programming Language :: Python
Classifier: Framework :: Odoo
Classifier: Framework :: Odoo :: 18.0
Classifier: License :: OSI Approved :: GNU Affero General Public License v3
